dagster_modal/__init__.py
dagster_modal/resources.py
dagster_modal-0.0.4.dist-info/METADATA
dagster_modal-0.0.4.dist-info/WHEEL
dagster_modal-0.0.4.dist-info/top_level.txt
dagster_modal-0.0.4.dist-info/RECORD
