Metadata-Version: 2.4
Name: dagster-modal
Version: 0.0.4
Summary: Dagster integration with Modal
Requires-Python: >=3.10
Requires-Dist: dagster-pipes>=1.7.0
Requires-Dist: dagster>=1.7.0
Requires-Dist: modal>=0.64.163
